circuit.v
`timescale 1ns / 1ps
`include "iob_lib.vh"

module circuit
  (
   `INPUT(rst,1),
   `INPUT(clk,1),
   `INPUT(en,1),
   `INPUT(x,32),
   `OUTPUT(y,32)
   );

   `SIGNAL(cnt, 7) //7-bit counter as iterator
   `SIGNAL(y_int, 32) //internal y
   `SIGNAL(y_int_n_1, 32) //y(n-1)
   `SIGNAL2OUT(y, y_int)//connect internal y to output
   
   //y shift register 
   `REG_ARE(clk, rst, 1'b0, en&(cnt!=99), y_int_n_1, y_int)

   //iteration counter
   `COUNTER_ARE(clk, rst, cnt!=99, cnt)

   //compute next why
   `COMB begin 
  
   	if(x[31]==1'b1) begin
   		y_int = y_int_n_1 - x;
   	end
 	else begin
   		y_int = y_int_n_1 + x;
   	end
     
   end
   
   
endmodule

circuit_tb.v
`timescale 1ns / 1ps
`include "iob_lib.vh"

module circuit_tb;

   `CLOCK(clk, 10)
   `RESET(rst, 1, 10)
   `SIGNAL(en, 1)
   `SIGNAL(x, 32)
   `SIGNAL_OUT(y, 32)

   integer i;
   
   initial begin
      $dumpfile("circuit.vcd");
      $dumpvars();
      en=0;
      for (i=0; i<100; i=i+1) begin
         @(posedge clk) #1 x=$random; en=1;
         @(posedge clk) #1 en=0;
         $display("%d: %d",i+1, y);
      end

      @(posedge clk) #100 $finish;

   end 

   circuit c0
     (
      .rst(rst),
      .clk(clk),
      .en(en),
      .x(x),
      .y(y)
      );


endmodule

circuit.vcd
$date
	Tue Nov 17 21:04:22 2020
$end
$version
	Icarus Verilog
$end
$timescale
	1ps
$end
$scope module circuit_tb $end
$var wire 32 ! y [31:0] $end
$var reg 1 " clk $end
$var reg 1 # en $end
$var reg 1 $ rst $end
$var reg 32 % x [31:0] $end
$var integer 32 & i [31:0] $end
$scope module c0 $end
$var wire 1 " clk $end
$var wire 1 # en $end
$var wire 1 $ rst $end
$var wire 32 ' x [31:0] $end
$var wire 32 ( y [31:0] $end
$var reg 7 ) cnt [6:0] $end
$var reg 32 * y_int [31:0] $end
$var reg 32 + y_int_n_1 [31:0] $end
$upscope $end
$upscope $end
$enddefinitions $end
#0
$dumpvars
bx +
bx *
bx )
bx (
bx '
b0 &
bx %
0$
0#
1"
bx !
$end
#1000
b0 )
b0 +
1$
#5000
0"
#10000
1"
#11000
b10010000101010011010100100100 !
b10010000101010011010100100100 (
b10010000101010011010100100100 *
1#
b10010000101010011010100100100 %
b10010000101010011010100100100 '
0$
#15000
0"
#20000
b100100001010100110101001001000 !
b100100001010100110101001001000 (
b100100001010100110101001001000 *
b1 )
b10010000101010011010100100100 +
1"
#21000
b1 &
0#
#25000
0"
#30000
b10 )
1"
#31000
b1010001100010111101011010100011 !
b1010001100010111101011010100011 (
b1010001100010111101011010100011 *
1#
b11000000100010010101111010000001 %
b11000000100010010101111010000001 '
#35000
0"
#40000
b10010001000000100111100000100010 !
b10010001000000100111100000100010 (
b10010001000000100111100000100010 *
b11 )
b1010001100010111101011010100011 +
1"
#41000
b10 &
0#
#45000
0"
#50000
b100 )
1"
#51000
b11001101000001110000000010011010 !
b11001101000001110000000010011010 (
b11001101000001110000000010011010 *
1#
b10000100100001001101011000001001 %
b10000100100001001101011000001001 '
#55000
0"
#60000
b1001000100000100010101010010001 !
b1001000100000100010101010010001 (
b1001000100000100010101010010001 *
b101 )
b11001101000001110000000010011010 +
1"
#61000
b11 &
0#
#65000
0"
#70000
b110 )
1"
#71000
b11011000101101010101000110111 !
b11011000101101010101000110111 (
b11011000101101010101000110111 *
1#
b10110001111100000101011001100011 %
b10110001111100000101011001100011 '
#75000
0"
#80000
b1101001001001100101001111010100 !
b1101001001001100101001111010100 (
b1101001001001100101001111010100 *
b111 )
b11011000101101010101000110111 +
1"
#81000
b100 &
0#
#85000
0"
#90000
b1000 )
1"
#91000
b100001110100000010010101000100 !
b100001110100000010010101000100 (
b100001110100000010010101000100 *
1#
b110101110010111101100001101 %
b110101110010111101100001101 '
#95000
0"
#100000
b101000100010011010000001010001 !
b101000100010011010000001010001 (
b101000100010011010000001010001 *
b1001 )
b100001110100000010010101000100 +
1"
#101000
b101 &
0#
#105000
0"
#110000
b1010 )
1"
#111000
b1101000101011111011111011010001 !
b1101000101011111011111011010001 (
b1101000101011111011111011010001 *
1#
b1000110110111111001100110001101 %
b1000110110111111001100110001101 '
#115000
0"
#120000
b10101111100011110101100001011110 !
b10101111100011110101100001011110 (
b10101111100011110101100001011110 *
b1011 )
b1101000101011111011111011010001 +
1"
#121000
b110 &
0#
#125000
0"
#130000
b1100 )
1"
#131000
b10110101111011010011101001101100 !
b10110101111011010011101001101100 (
b10110101111011010011101001101100 *
1#
b10110010110000101000010001100101 %
b10110010110000101000010001100101 '
#135000
0"
#140000
b11001010101011011000000111 !
b11001010101011011000000111 (
b11001010101011011000000111 *
b1101 )
b10110101111011010011101001101100 +
1"
#141000
b111 &
0#
#145000
0"
#150000
b1110 )
1"
#151000
b101100101101011110100001011010 !
b101100101101011110100001011010 (
b101100101101011110100001011010 *
1#
b10001001001101110101001000010010 %
b10001001001101110101001000010010 '
#155000
0"
#160000
b10100011011111101001011001001000 !
b10100011011111101001011001001000 (
b10100011011111101001011001001000 *
b1111 )
b101100101101011110100001011010 +
1"
#161000
b1000 &
0#
#165000
0"
#170000
b10000 )
1"
#171000
b101101101010011100101101011011 !
b101101101010011100101101011011 (
b101101101010011100101101011011 *
1#
b111100111110001100000001 %
b111100111110001100000001 '
#175000
0"
#180000
b101110100111011010111001011100 !
b101110100111011010111001011100 (
b101110100111011010111001011100 *
b10001 )
b101101101010011100101101011011 +
1"
#181000
b1001 &
0#
#185000
0"
#190000
b10010 )
1"
#191000
b110100100000011001100001101000 !
b110100100000011001100001101000 (
b110100100000011001100001101000 *
1#
b110110101111100110100001101 %
b110110101111100110100001101 '
#195000
0"
#200000
b111011010110010110010101110101 !
b111011010110010110010101110101 (
b111011010110010110010101110101 *
b10011 )
b110100100000011001100001101000 +
1"
#201000
b1010 &
0#
#205000
0"
#210000
b10100 )
1"
#211000
b1101111101001011000100111011110 !
b1101111101001011000100111011110 (
b1101111101001011000100111011110 *
1#
b111011001000111111000101110110 %
b111011001000111111000101110110 '
#215000
0"
#220000
b10101010110010010111101101010100 !
b10101010110010010111101101010100 (
b10101010110010010111101101010100 *
b10101 )
b1101111101001011000100111011110 +
1"
#221000
b1011 &
0#
#225000
0"
#230000
b10110 )
1"
#231000
b10001110001100110101011100011011 !
b10001110001100110101011100011011 (
b10001110001100110101011100011011 *
1#
b11110100011011100110100111101 %
b11110100011011100110100111101 '
#235000
0"
#240000
b10101100110000010010010001011000 !
b10101100110000010010010001011000 (
b10101100110000010010010001011000 *
b10111 )
b10001110001100110101011100011011 +
1"
#241000
b1100 &
0#
#245000
0"
#250000
b11000 )
1"
#251000
b101000001111010111100001000 !
b101000001111010111100001000 (
b101000001111010111100001000 *
1#
b1110110110101000101011111101101 %
b1110110110101000101011111101101 '
#255000
0"
#260000
b1111011110111000000011011110101 !
b1111011110111000000011011110101 (
b1111011110111000000011011110101 *
b11001 )
b101000001111010111100001000 +
1"
#261000
b1101 &
0#
#265000
0"
#270000
b11010 )
1"
#271000
b1001011001101011010011010010100 !
b1001011001101011010011010010100 (
b1001011001101011010011010010100 *
1#
b1000110001011011111011110001100 %
b1000110001011011111011110001100 '
#275000
0"
#280000
b10010001011000111001111000100000 !
b10010001011000111001111000100000 (
b10010001011000111001111000100000 *
b11011 )
b1001011001101011010011010010100 +
1"
#281000
b1110 &
0#
#285000
0"
#290000
b11100 )
1"
#291000
b11001000001100111001000010001101 !
b11001000001100111001000010001101 (
b11001000001100111001000010001101 *
1#
b1111100111111011110100111111001 %
b1111100111111011110100111111001 '
#295000
0"
#300000
b1000101001100010111101010000110 !
b1000101001100010111101010000110 (
b1000101001100010111101010000110 *
b11101 )
b11001000001100111001000010001101 +
1"
#301000
b1111 &
0#
#305000
0"
#310000
b11110 )
1"
#311000
b11100100111111000110101111000111 !
b11100100111111000110101111000111 (
b11100100111111000110101111000111 *
1#
b11100011001101110010010011000110 %
b11100011001101110010010011000110 '
#315000
0"
#320000
b1110001010100011100000001 !
b1110001010100011100000001 (
b1110001010100011100000001 *
b11111 )
b11100100111111000110101111000111 +
1"
#321000
b10000 &
0#
#325000
0"
#330000
b100000 )
1"
#331000
b10000001001110011100000010 !
b10000001001110011100000010 (
b10000001001110011100000010 *
1#
b11100010111101111000010011000101 %
b11100010111101111000010011000101 '
#335000
0"
#340000
b11111000011010110001000111101 !
b11111000011010110001000111101 (
b11111000011010110001000111101 *
b100001 )
b10000001001110011100000010 +
1"
#341000
b10001 &
0#
#345000
0"
#350000
b100010 )
1"
#351000
b101100111100010001010001011000 !
b101100111100010001010001011000 (
b101100111100010001010001011000 *
1#
b11010101000100111101001010101010 %
b11010101000100111101001010101010 '
#355000
0"
#360000
b1010111110111010100000110101110 !
b1010111110111010100000110101110 (
b1010111110111010100000110101110 *
b100011 )
b101100111100010001010001011000 +
1"
#361000
b10010 &
0#
#365000
0"
#370000
b100100 )
1"
#371000
b10011111101000010000110000111101 !
b10011111101000010000110000111101 (
b10011111101000010000110000111101 *
1#
b1110010101011111111011111100101 %
b1110010101011111111011111100101 '
#375000
0"
#380000
b10010010100010000010000100010 !
b10010010100010000010000100010 (
b10010010100010000010000100010 *
b100101 )
b10011111101000010000110000111101 +
1"
#381000
b10011 &
0#
#385000
0"
#390000
b100110 )
1"
#391000
b11100011110011101001100111000110 !
b11100011110011101001100111000110 (
b11100011110011101001100111000110 *
1#
b10111011110100100111001001110111 %
b10111011110100100111001001110111 '
#395000
0"
#400000
b100111111111000010011101001111 !
b100111111111000010011101001111 (
b100111111111000010011101001111 *
b100111 )
b11100011110011101001100111000110 +
1"
#401000
b10100 &
0#
#405000
0"
#410000
b101000 )
1"
#411000
b1011010100110111100001110110100 !
b1011010100110111100001110110100 (
b1011010100110111100001110110100 *
1#
b10001001001100101101011000010010 %
b10001001001100101101011000010010 '
#415000
0"
#420000
b11010001011010001110110110100010 !
b11010001011010001110110110100010 (
b11010001011010001110110110100010 *
b101001 )
b1011010100110111100001110110100 +
1"
#421000
b10101 &
0#
#425000
0"
#430000
b101010 )
1"
#431000
b10100010100010001001111101000011 !
b10100010100010001001111101000011 (
b10100010100010001001111101000011 *
1#
b1000111111011001101101110001111 %
b1000111111011001101101110001111 '
#435000
0"
#440000
b11101010011101010111101011010010 !
b11101010011101010111101011010010 (
b11101010011101010111101011010010 *
b101011 )
b10100010100010001001111101000011 +
1"
#441000
b10110 &
0#
#445000
0"
#450000
b101100 )
1"
#451000
b11011101110010000100100110101 !
b11011101110010000100100110101 (
b11011101110010000100100110101 *
1#
b1111001001100000110100111110010 %
b1111001001100000110100111110010 '
#455000
0"
#460000
b10010100111010010111001100100111 !
b10010100111010010111001100100111 (
b10010100111010010111001100100111 *
b101101 )
b11011101110010000100100110101 +
1"
#461000
b10111 &
0#
#465000
0"
#470000
b101110 )
1"
#471000
b110100010000100111001001100111 !
b110100010000100111001001100111 (
b110100010000100111001001100111 *
1#
b11100111011101101001011011001110 %
b11100111011101101001011011001110 '
#475000
0"
#480000
b1001100110010111101101110011001 !
b1001100110010111101101110011001 (
b1001100110010111101101110011001 *
b101111 )
b110100010000100111001001100111 +
1"
#481000
b11000 &
0#
#485000
0"
#490000
b110000 )
1"
#491000
b1000000010000011111011101111111 !
b1000000010000011111011101111111 (
b1000000010000011111011101111111 *
1#
b11110100000000000111101011101000 %
b11110100000000000111101011101000 '
#495000
0"
#500000
b1001100010000010111110010010111 !
b1001100010000010111110010010111 (
b1001100010000010111110010010111 *
b110001 )
b1000000010000011111011101111111 +
1"
#501000
b11001 &
0#
#505000
0"
#510000
b110010 )
1"
#511000
b1011101011101111010100010111010 !
b1011101011101111010100010111010 (
b1011101011101111010100010111010 *
1#
b11100010110010100100111011000101 %
b11100010110010100100111011000101 '
#515000
0"
#520000
b1111010101011010101100111110101 !
b1111010101011010101100111110101 (
b1111010101011010101100111110101 *
b110011 )
b1011101011101111010100010111010 +
1"
#521000
b11010 &
0#
#525000
0"
#530000
b110100 )
1"
#531000
b10001011110011111111001000010110 !
b10001011110011111111001000010110 (
b10001011110011111111001000010110 *
1#
b101110010110000100100101011100 %
b101110010110000100100101011100 '
#535000
0"
#540000
b10111010001010000011101101110010 !
b10111010001010000011101101110010 (
b10111010001010000011101101110010 *
b110101 )
b10001011110011111111001000010110 +
1"
#541000
b11011 &
0#
#545000
0"
#550000
b110110 )
1"
#551000
b10101101010000011100100101011001 !
b10101101010000011100100101011001 (
b10101101010000011100100101011001 *
1#
b11011110100011100010100010111101 %
b11011110100011100010100010111101 '
#555000
0"
#560000
b11001110101100111010000010011100 !
b11001110101100111010000010011100 (
b11001110101100111010000010011100 *
b110111 )
b10101101010000011100100101011001 +
1"
#561000
b11100 &
0#
#565000
0"
#570000
b111000 )
1"
#571000
b10110100101100111000100101100 !
b10110100101100111000100101100 (
b10110100101100111000100101100 *
1#
b10010110101010110101100000101101 %
b10010110101010110101100000101101 '
#575000
0"
#580000
b1111111111010110001100011111111 !
b1111111111010110001100011111111 (
b1111111111010110001100011111111 *
b111001 )
b10110100101100111000100101100 +
1"
#581000
b11101 &
0#
#585000
0"
#590000
b111010 )
1"
#591000
b1100011111011110100101011000111 !
b1100011111011110100101011000111 (
b1100011111011110100101011000111 *
1#
b10110010101001110010011001100101 %
b10110010101001110010011001100101 '
#595000
0"
#600000
b10110001010010000010010001100010 !
b10110001010010000010010001100010 (
b10110001010010000010010001100010 *
b111011 )
b1100011111011110100101011000111 +
1"
#601000
b11110 &
0#
#605000
0"
#610000
b111100 )
1"
#611000
b10110001111111111110100001100100 !
b10110001111111111110100001100100 (
b10110001111111111110100001100100 *
1#
b10110001111011110110001001100011 %
b10110001111011110110001001100011 '
#615000
0"
#620000
b100001000011000000001 !
b100001000011000000001 (
b100001000011000000001 *
b111101 )
b10110001111111111110100001100100 +
1"
#621000
b11111 &
0#
#625000
0"
#630000
b111110 )
1"
#631000
b10110111011100110110111101101110 !
b10110111011100110110111101101110 (
b10110111011100110110111101101110 *
1#
b101011100111000011100001010 %
b101011100111000011100001010 '
#635000
0"
#640000
b10111100111001101111011001111000 !
b10111100111001101111011001111000 (
b10111100111001101111011001111000 *
b111111 )
b10110111011100110110111101101110 +
1"
#641000
b100000 &
0#
#645000
0"
#650000
b1000000 )
1"
#651000
b11110111001110000100110011101110 !
b11110111001110000100110011101110 (
b11110111001110000100110011101110 *
1#
b11000000001110110010001010000000 %
b11000000001110110010001010000000 '
#655000
0"
#660000
b110110111111010010101001101110 !
b110110111111010010101001101110 (
b110110111111010010101001101110 *
b1000001 )
b11110111001110000100110011101110 +
1"
#661000
b100001 &
0#
#665000
0"
#670000
b1000010 )
1"
#671000
b111100111000110111000001110 !
b111100111000110111000001110 (
b111100111000110111000001110 *
1#
b10000011001000010000100100000 %
b10000011001000010000100100000 '
#675000
0"
#680000
b11000000000001000111100101110 !
b11000000000001000111100101110 (
b11000000000001000111100101110 *
b1000011 )
b111100111000110111000001110 +
1"
#681000
b100010 &
0#
#685000
0"
#690000
b1000100 )
1"
#691000
b1011101000101001011001110111000 !
b1011101000101001011001110111000 (
b1011101000101001011001110111000 *
1#
b1010101011110000100010110101010 %
b1010101011110000100010110101010 '
#695000
0"
#700000
b10110010100011001111100101100010 !
b10110010100011001111100101100010 (
b10110010100011001111100101100010 *
b1000101 )
b1011101000101001011001110111000 +
1"
#701000
b100011 &
0#
#705000
0"
#710000
b1000110 )
1"
#711000
b10001110010001111110011100011011 !
b10001110010001111110011100011011 (
b10001110010001111110011100011011 *
1#
b11001110110011001100110010011101 %
b11001110110011001100110010011101 '
#715000
0"
#720000
b10111111011110110001101001111110 !
b10111111011110110001101001111110 (
b10111111011110110001101001111110 *
b1000111 )
b10001110010001111110011100011011 +
1"
#721000
b100100 &
0#
#725000
0"
#730000
b1001000 )
1"
#731000
b11000011001001111010100010000101 !
b11000011001001111010100010000101 (
b11000011001001111010100010000101 *
1#
b11001011001000000011111010010110 %
b11001011001000000011111010010110 '
#735000
0"
#740000
b11111000000001110110100111101111 !
b11111000000001110110100111101111 (
b11111000000001110110100111101111 *
b1001001 )
b11000011001001111010100010000101 +
1"
#741000
b100101 &
0#
#745000
0"
#750000
b1001010 )
1"
#751000
b111001101000111111000001110010 !
b111001101000111111000001110010 (
b111001101000111111000001110010 *
1#
b10001001100000111011100000010011 %
b10001001100000111011100000010011 '
#755000
0"
#760000
b10110000001000000011100001011111 !
b10110000001000000011100001011111 (
b10110000001000000011100001011111 *
b1001011 )
b111001101000111111000001110010 +
1"
#761000
b100110 &
0#
#765000
0"
#770000
b1001100 )
1"
#771000
b10110010111001111011100001100101 !
b10110010111001111011100001100101 (
b10110010111001111011100001100101 *
1#
b10000110101111000011100000001101 %
b10000110101111000011100000001101 '
#775000
0"
#780000
b101100001010111000000001011000 !
b101100001010111000000001011000 (
b101100001010111000000001011000 *
b1001101 )
b10110010111001111011100001100101 +
1"
#781000
b100111 &
0#
#785000
0"
#790000
b1001110 )
1"
#791000
b1001001111111110001000010010 !
b1001001111111110001000010010 (
b1001001111111110001000010010 *
1#
b10101001101001111101011001010011 %
b10101001101001111101011001010011 '
#795000
0"
#800000
b1011111100110000000101110111111 !
b1011111100110000000101110111111 (
b1011111100110000000101110111111 *
b1001111 )
b1001001111111110001000010010 +
1"
#801000
b101000 &
0#
#805000
0"
#810000
b1010000 )
1"
#811000
b111110110111111011111101111101 !
b111110110111111011111101111101 (
b111110110111111011111101111101 *
1#
b110101100111111101110101101011 %
b110101100111111101110101101011 '
#815000
0"
#820000
b1110100011111111001110011101000 !
b1110100011111111001110011101000 (
b1110100011111111001110011101000 *
b1010001 )
b111110110111111011111101111101 +
1"
#821000
b101001 &
0#
#825000
0"
#830000
b1010010 )
1"
#831000
b1010100001110011001010010101000 !
b1010100001110011001010010101000 (
b1010100001110011001010010101000 *
1#
b11101010101001100010101011010101 %
b11101010101001100010101011010101 '
#835000
0"
#840000
b1101001100100110110100111010011 !
b1101001100100110110100111010011 (
b1101001100100110110100111010011 *
b1010011 )
b1010100001110011001010010101000 +
1"
#841000
b101010 &
0#
#845000
0"
#850000
b1010100 )
1"
#851000
b11010011001000100100101010100110 !
b11010011001000100100101010100110 (
b11010011001000100100101010100110 *
1#
b10000001000101110100101000000010 %
b10000001000101110100101000000010 '
#855000
0"
#860000
b1010010000010110000000010100100 !
b1010010000010110000000010100100 (
b1010010000010110000000010100100 *
b1010101 )
b11010011001000100100101010100110 +
1"
#861000
b101011 &
0#
#865000
0"
#870000
b1010110 )
1"
#871000
b11111011110011000000101111111000 !
b11111011110011000000101111111000 (
b11111011110011000000101111111000 *
1#
b11010111010101100011111010101110 %
b11010111010101100011111010101110 '
#875000
0"
#880000
b100100011101011100110101001010 !
b100100011101011100110101001010 (
b100100011101011100110101001010 *
b1010111 )
b11111011110011000000101111111000 +
1"
#881000
b101100 &
0#
#885000
0"
#890000
b1011000 )
1"
#891000
b1010110010111111010100010101 !
b1010110010111111010100010101 (
b1010110010111111010100010101 *
1#
b1110111111111110100100011101 %
b1110111111111110100100011101 '
#895000
0"
#900000
b11001110010111101111000110010 !
b11001110010111101111000110010 (
b11001110010111101111000110010 *
b1011001 )
b1010110010111111010100010101 +
1"
#901000
b101101 &
0#
#905000
0"
#910000
b1011010 )
1"
#911000
b100011000001101000001001000110 !
b100011000001101000001001000110 (
b100011000001101000001001000110 *
1#
b11100111110001010111001011001111 %
b11100111110001010111001011001111 '
#915000
0"
#920000
b111011010000010000111101110111 !
b111011010000010000111101110111 (
b111011010000010000111101110111 *
b1011011 )
b100011000001101000001001000110 +
1"
#921000
b101110 &
0#
#925000
0"
#930000
b1011100 )
1"
#931000
b110100100010101100101101101001 !
b110100100010101100101101101001 (
b110100100010101100101101101001 *
1#
b10001100001000100100100100011 %
b10001100001000100100100100011 '
#935000
0"
#940000
b1000110000011110001010010001100 !
b1000110000011110001010010001100 (
b1000110000011110001010010001100 *
b1011101 )
b110100100010101100101101101001 +
1"
#941000
b101111 &
0#
#945000
0"
#950000
b1011110 )
1"
#951000
b111001100101000011000001110011 !
b111001100101000011000001110011 (
b111001100101000011000001110011 *
1#
b101000010010110010100001010 %
b101000010010110010100001010 '
#955000
0"
#960000
b111110100111011001010101111101 !
b111110100111011001010101111101 (
b111110100111011001010101111101 *
b1011111 )
b111001100101000011000001110011 +
1"
#961000
b110000 &
0#
#965000
0"
#970000
b1100000 )
1"
#971000
b1010100001000010010010110101001 !
b1010100001000010010010110101001 (
b1010100001000010010010110101001 *
1#
b11100101011100110000101011001010 %
b11100101011100110000101011001010 '
#975000
0"
#980000
b1101110101011100001101011011111 !
b1101110101011100001101011011111 (
b1101110101011100001101011011111 *
b1100001 )
b1010100001000010010010110101001 +
1"
#981000
b110001 &
0#
#985000
0"
#990000
b1100010 )
1"
#991000
b10110101111011111101100101101101 !
b10110101111011111101100101101101 (
b10110101111011111101100101101101 *
1#
b10011110001100010100110000111100 %
b10011110001100010100110000111100 '
#995000
0"
#1000000
b10111101111101000110100110001 !
b10111101111101000110100110001 (
b10111101111101000110100110001 *
b1100011 )
b10110101111011111101100101101101 +
1"
#1001000
b110010 &
0#
#1005000
0"
#1010000
1"
#1011000
b101111010110001001011101011111 !
b101111010110001001011101011111 (
b101111010110001001011101011111 *
1#
b1111001011010001011110111110010 %
b1111001011010001011110111110010 '
#1015000
0"
#1020000
1"
#1021000
b110011 &
0#
#1025000
0"
#1030000
1"
#1031000
b11111011000111100011101011110111 !
b11111011000111100011101011110111 (
b11111011000111100011101011110111 *
1#
b1000101001011100110000110001010 %
b1000101001011100110000110001010 '
#1035000
0"
#1040000
1"
#1041000
b110100 &
0#
#1045000
0"
#1050000
1"
#1051000
b11010110101101001000110010101110 !
b11010110101101001000110010101110 (
b11010110101101001000110010101110 *
1#
b100000110001001011001101000001 %
b100000110001001011001101000001 '
#1055000
0"
#1060000
1"
#1061000
b110101 &
0#
#1065000
0"
#1070000
1"
#1071000
b11001001101001001010010010010101 !
b11001001101001001010010010010101 (
b11001001101001001010010010010101 *
1#
b11101100010010110011010011011000 %
b11101100010010110011010011011000 '
#1075000
0"
#1080000
1"
#1081000
b110110 &
0#
#1085000
0"
#1090000
1"
#1091000
b11110010000100001100110011100101 !
b11110010000100001100110011100101 (
b11110010000100001100110011100101 *
1#
b111100001000001111001101111000 %
b111100001000001111001101111000 '
#1095000
0"
#1100000
1"
#1101000
b110111 &
0#
#1105000
0"
#1110000
1"
#1111000
b11110001011001011100011011100100 !
b11110001011001011100011011100100 (
b11110001011001011100011011100100 *
1#
b11000100100010100001001010001001 %
b11000100100010100001001010001001 '
#1115000
0"
#1120000
1"
#1121000
b111000 &
0#
#1125000
0"
#1130000
1"
#1131000
b101011101101001110011101011000 !
b101011101101001110011101011000 (
b101011101101001110011101011000 *
1#
b1110101110001010000110111101011 %
b1110101110001010000110111101011 '
#1135000
0"
#1140000
1"
#1141000
b111001 &
0#
#1145000
0"
#1150000
1"
#1151000
b10000111100100011111100100011 !
b10000111100100011111100100011 (
b10000111100100011111100100011 *
1#
b1011011000000100110010110110110 %
b1011011000000100110010110110110 '
#1155000
0"
#1160000
1"
#1161000
b111010 &
0#
#1165000
0"
#1170000
1"
#1171000
b11001001110111101001100110011 !
b11001001110111101001100110011 (
b11001001110111101001100110011 *
1#
b1100011010010111111100111000110 %
b1100011010010111111100111000110 '
#1175000
0"
#1180000
1"
#1181000
b111011 &
0#
#1185000
0"
#1190000
1"
#1191000
b1101000001001110110100011011 !
b1101000001001110110100011011 (
b1101000001001110110100011011 *
1#
b1010111000101010001001110101110 %
b1010111000101010001001110101110 '
#1195000
0"
#1200000
1"
#1201000
b111100 &
0#
#1205000
0"
#1210000
1"
#1211000
b11010111011110101101011010110001 !
b11010111011110101101011010110001 (
b11010111011110101101011010110001 *
1#
b11011110011101010000001010111100 %
b11011110011101010000001010111100 '
#1215000
0"
#1220000
1"
#1221000
b111101 &
0#
#1225000
0"
#1230000
1"
#1231000
b11001010111111111011011010010111 !
b11001010111111111011011010010111 (
b11001010111111111011011010010111 *
1#
b10101000011111101110100101010 %
b10101000011111101110100101010 '
#1235000
0"
#1240000
1"
#1241000
b111110 &
0#
#1245000
0"
#1250000
1"
#1251000
b110000000110000011111101100010 !
b110000000110000011111101100010 (
b110000000110000011111101100010 *
1#
b10000101110101111001101000001011 %
b10000101110101111001101000001011 '
#1255000
0"
#1260000
1"
#1261000
b111111 &
0#
#1265000
0"
#1270000
1"
#1271000
b11111101010110000001101011111100 !
b11111101010110000001101011111100 (
b11111101010110000001101011111100 *
1#
b10111000100101111011111001110001 %
b10111000100101111011111001110001 '
#1275000
0"
#1280000
1"
#1281000
b1000000 &
0#
#1285000
0"
#1290000
1"
#1291000
b11111000111000100001101011110010 !
b11111000111000100001101011110010 (
b11111000111000100001101011110010 *
1#
b1000010111100100100000110000101 %
b1000010111100100100000110000101 '
#1295000
0"
#1300000
1"
#1301000
b1000001 &
0#
#1305000
0"
#1310000
1"
#1311000
b11011101111000100010111010111100 !
b11011101111000100010111010111100 (
b11011101111000100010111010111100 *
1#
b100111111100100101010101001111 %
b100111111100100101010101001111 '
#1315000
0"
#1320000
1"
#1321000
b1000010 &
0#
#1325000
0"
#1330000
1"
#1331000
b11000001000110111100100110010 !
b11000001000110111100100110010 (
b11000001000110111100100110010 *
1#
b10011101110011000110000000111011 %
b10011101110011000110000000111011 '
#1335000
0"
#1340000
1"
#1341000
b1000011 &
0#
#1345000
0"
#1350000
1"
#1351000
b11010010111101100000110010100111 !
b11010010111101100000110010100111 (
b11010010111101100000110010100111 *
1#
b11101000001100011001100111010 %
b11101000001100011001100111010 '
#1355000
0"
#1360000
1"
#1361000
b1000100 &
0#
#1365000
0"
#1370000
1"
#1371000
b11110110110011001010011011101111 !
b11110110110011001010011011101111 (
b11110110110011001010011011101111 *
1#
b10111111001000110011001001111110 %
b10111111001000110011001001111110 '
#1375000
0"
#1380000
1"
#1381000
b1000101 &
0#
#1385000
0"
#1390000
1"
#1391000
b11000000100110100010010010000010 !
b11000000100110100010010010000010 (
b11000000100110100010010010000010 *
1#
b1010101010100100101100010101 %
b1010101010100100101100010101 '
#1395000
0"
#1400000
1"
#1401000
b1000110 &
0#
#1405000
0"
#1410000
1"
#1411000
b101110110010010111010101011110 !
b101110110010010111010101011110 (
b101110110010010111010101011110 *
1#
b1111000110110011001101111110001 %
b1111000110110011001101111110001 '
#1415000
0"
#1420000
1"
#1421000
b1000111 &
0#
#1425000
0"
#1430000
1"
#1431000
b100010100011000010010101000110 !
b100010100011000010010101000110 (
b100010100011000010010101000110 *
1#
b1101100100111000100101111011001 %
b1101100100111000100101111011001 '
#1435000
0"
#1440000
1"
#1441000
b1001000 &
0#
#1445000
0"
#1450000
1"
#1451000
b11100111000100101110000011001111 !
b11100111000100101110000011001111 (
b11100111000100101110000011001111 *
1#
b110001001000110000011101100010 %
b110001001000110000011101100010 '
#1455000
0"
#1460000
1"
#1461000
b1001001 &
0#
#1465000
0"
#1470000
1"
#1471000
b11011100001001011101010010111001 !
b11011100001001011101010010111001 (
b11011100001001011101010010111001 *
1#
b100110001101011111101101001100 %
b100110001101011111101101001100 '
#1475000
0"
#1480000
1"
#1481000
b1001010 &
0#
#1485000
0"
#1490000
1"
#1491000
b101100100010010111100001100 !
b101100100010010111100001100 (
b101100100010010111100001100 *
1#
b1001111101000010101010110011111 %
b1001111101000010101010110011111 '
#1495000
0"
#1500000
1"
#1501000
b1001011 &
0#
#1505000
0"
#1510000
1"
#1511000
b11111101101010010111101011111100 !
b11111101101010010111101011111100 (
b11111101101010010111101011111100 *
1#
b1000111101110011010000110001111 %
b1000111101110011010000110001111 '
#1515000
0"
#1520000
1"
#1521000
b1001100 &
0#
#1525000
0"
#1530000
1"
#1531000
b110010010111011000001101100101 !
b110010010111011000001101100101 (
b110010010111011000001101100101 *
1#
b1111100011011011010100111111000 %
b1111100011011011010100111111000 '
#1535000
0"
#1540000
1"
#1541000
b1001101 &
0#
#1545000
0"
#1550000
1"
#1551000
b11011010001000100111100010110110 !
b11011010001000100111100010110110 (
b11011010001000100111100010110110 *
1#
b11011011110011010110000010110111 %
b11011011110011010110000010110111 '
#1555000
0"
#1560000
1"
#1561000
b1001110 &
0#
#1565000
0"
#1570000
1"
#1571000
b11100110001010111000001011001110 !
b11100110001010111000001011001110 (
b11100110001010111000001011001110 *
1#
b11001111110001000101011010011111 %
b11001111110001000101011010011111 '
#1575000
0"
#1580000
1"
#1581000
b1001111 &
0#
#1585000
0"
#1590000
1"
#1591000
b111011100100100010100010001 !
b111011100100100010100010001 (
b111011100100100010100010001 *
1#
b10101110011111011001010001011100 %
b10101110011111011001010001011100 '
#1595000
0"
#1600000
1"
#1601000
b1010000 &
0#
#1605000
0"
#1610000
1"
#1611000
b1000001001000001100100010010 !
b1000001001000001100100010010 (
b1000001001000001100100010010 *
1#
b10101101110010111100000001011011 %
b10101101110010111100000001011011 '
#1615000
0"
#1620000
1"
#1621000
b1010001 &
0#
#1625000
0"
#1630000
1"
#1631000
b11111010110011100001000011110110 !
b11111010110011100001000011110110 (
b11111010110011100001000011110110 *
1#
b1000100110111100011011110001001 %
b1000100110111100011011110001001 '
#1635000
0"
#1640000
1"
#1641000
b1010010 &
0#
#1645000
0"
#1650000
1"
#1651000
b10001010000011010011100100100 !
b10001010000011010011100100100 (
b10001010000011010011100100100 *
1#
b10100100101011100011001001001001 %
b10100100101011100011001001001001 '
#1655000
0"
#1660000
1"
#1661000
b1010011 &
0#
#1665000
0"
#1670000
1"
